  1           0 LOAD_NAME                0 (print)
              2 LOAD_NAME                1 (b)
              4 CALL_FUNCTION            1
              6 POP_TOP

  2           8 LOAD_CONST               0 (3)
             10 STORE_NAME               2 (a)

  3          12 LOAD_NAME                0 (print)
             14 LOAD_NAME                2 (a)
             16 CALL_FUNCTION            1
             18 POP_TOP

  5          20 LOAD_NAME                2 (a)
             22 LOAD_CONST               0 (3)
             24 COMPARE_OP               2 (==)
             26 POP_JUMP_IF_FALSE       38

  6          28 LOAD_NAME                0 (print)
             30 LOAD_CONST               1 ('a == 3')
             32 CALL_FUNCTION            1
             34 POP_TOP
             36 JUMP_FORWARD             8 (to 46)

  8     >>   38 LOAD_NAME                0 (print)
             40 LOAD_CONST               2 ('a != 3')
             42 CALL_FUNCTION            1
             44 POP_TOP

 10     >>   46 LOAD_NAME                3 (range)
             48 LOAD_CONST               0 (3)
             50 CALL_FUNCTION            1
             52 GET_ITER
        >>   54 FOR_ITER                12 (to 68)
             56 STORE_NAME               4 (n)

 11          58 LOAD_NAME                0 (print)
             60 LOAD_NAME                4 (n)
             62 CALL_FUNCTION            1
             64 POP_TOP
             66 JUMP_ABSOLUTE           54

 13     >>   68 LOAD_CONST               3 (1)
             70 STORE_NAME               4 (n)

 14     >>   72 LOAD_NAME                4 (n)
             74 LOAD_CONST               4 (10)
             76 COMPARE_OP               0 (<)
             78 POP_JUMP_IF_FALSE       98

 15          80 LOAD_NAME                0 (print)
             82 LOAD_NAME                4 (n)
             84 CALL_FUNCTION            1
             86 POP_TOP

 16          88 LOAD_NAME                4 (n)
             90 LOAD_CONST               3 (1)
             92 INPLACE_ADD
             94 STORE_NAME               4 (n)
             96 JUMP_ABSOLUTE           72

 18     >>   98 LOAD_CONST               5 (<code object test at 0x7f54354ba500, file "<disassembly>", line 18>)
            100 LOAD_CONST               6 ('test')
            102 MAKE_FUNCTION            0
            104 STORE_NAME               5 (test)
            106 LOAD_CONST               7 (None)
            108 RETURN_VALUE
